{"notes": "Includes bibliographical references (p. 341-343) and index.", "isbn10": "0125153902", "urls_text": "", "publisher_name": "Academic Press", "topic": "math", "dewey_normal": "332.632", "publisher_id": "academic_press", "category": "other subjects", "language": "eng", "dewey_decimal": "332.632", "title_long": "", "publisher_text": "San Diego : Academic Press, 1996.", "summary": "", "book_id": "an_introduction_to_the_mathematics_of_financial_derivatives", "copies": 1, "awards_text": "", "marc_enc_level": "", "edition_info": "", "subject_ids": ["derivative_securities_mathematics"], "lcc_number": "", "isbn13": "9780125153904", "physical_description_text": "xxi, 352 p. : ill. ; 24 cm.", "title_latin": "An introduction to the mathematics of financial derivatives", "author_data": [{"name": "Neftci, S N.", "id": "neftci_s_n"}], "title": "An introduction to the mathematics of financial derivatives", "shelf": "3.3"}