{"notes": "Previous ed.: Core Java 2. 7th ed.\n\n\"Revised and updated for Java SE 6\"--Cover.\n\nIncludes index.\n\nv. 1. Fundamentals -- v. 2. Advanced features.", "isbn10": "0132354799", "urls_text": "", "publisher_name": "Prentice Hall/Sun Microsystems Press", "topic": "java", "dewey_normal": "5.133", "publisher_id": "prentice_hall_sun_microsystems", "category": "languages", "language": "eng", "dewey_decimal": "005.13/3", "title_long": "", "publisher_text": "Upper Saddle River, NJ : Prentice Hall/Sun Microsystems Press, c2008.", "summary": "", "book_id": "core_java_advanced_features", "copies": 1, "awards_text": "", "marc_enc_level": "", "edition_info": "(v. 2)", "subject_ids": ["java_computer_program_language"], "lcc_number": "QA76.73", "isbn13": "9780132354790", "physical_description_text": "2 v. : ill. ; 24 cm.", "title_latin": "Core Java", "author_data": [{"name": "Horstmann, Cay S.", "id": "horstmann_cay_s"}, {"name": "Cornell, Gary", "id": "cornell_gary"}], "title": "Core Java", "shelf": "5.2"}